{
  "id": "סלט-תמרים-וצנוניות-imported",
  "title": "סלט תמרים וצנוניות:",
  "category": "סלטים",
  "ingredients": [
    "7 תמרים לחים (מאריזות קפואות) מקולפים , מתקלפים בקלות חתוכים לרבעים",
    "לרוחב",
    "7 תמרים צהובים (לאחר שהוקפאו לחצי שעה) חתוכים לרבעים לרוחב",
    "10 צנוניות פרוסות לטבעות כמה שיותר דקות",
    "גרעיני רימון מחצי רימון",
    "נבטי צנונית",
    "נבטי אפונה (ניתן להחליף עם סוג אחר או לוותר)",
    "לרוטב",
    "3 כפות שמן זית",
    "מיץ מחצי לימון",
    "מלח ופלפל שחור גרוס",
    "1 כף סילאן"
  ],
  "instructions": "1. מערבבים את כל הרכיבים יחד בקערה 2. את הרוטב טורפים במטרפה וטועמים 3. מערבבים יחד ומגישים",
  "audioUrl": null,
  "createdAt": "2026-04-10T00:00:00.000Z"
}